fastapi_redis_rate_limiter/__init__.py
fastapi_redis_rate_limiter/redis_client.py
fastapi_redis_rate_limiter/redis_rate_limiter_middleware.py
fastapi_redis_rate_limiter-1.0.1.dist-info/LICENSE
fastapi_redis_rate_limiter-1.0.1.dist-info/METADATA
fastapi_redis_rate_limiter-1.0.1.dist-info/WHEEL
fastapi_redis_rate_limiter-1.0.1.dist-info/top_level.txt
fastapi_redis_rate_limiter-1.0.1.dist-info/RECORD
