Metadata-Version: 2.1
Name: fastapi-redis-rate-limiter
Version: 1.0.1
Summary: fastapi rate limiter middleware
Home-page: https://github.com/iunary/fastapi-redis-rate-limiter
Author: Yusuf
Author-email: contact@yusuf.im
License: MIT
Keywords: fastapi rate limiter,redis,middleware
Platform: UNKNOWN
Classifier: Programming Language :: Python :: 3
Classifier: Operating System :: OS Independent
Requires-Python: >=3.8
License-File: LICENSE
